CHANGES.txt
README.txt
buildout.cfg
setup.py
src/hurry/__init__.py
src/hurry.zopetinymce.egg-info/PKG-INFO
src/hurry.zopetinymce.egg-info/SOURCES.txt
src/hurry.zopetinymce.egg-info/dependency_links.txt
src/hurry.zopetinymce.egg-info/namespace_packages.txt
src/hurry.zopetinymce.egg-info/not-zip-safe
src/hurry.zopetinymce.egg-info/requires.txt
src/hurry.zopetinymce.egg-info/top_level.txt
src/hurry/zopetinymce/__init__.py
src/hurry/zopetinymce/configure.zcml