Metadata-Version: 1.0
Name: hurry.zopetinymce
Version: 0.1
Summary: Zope integration for hurry.tinymce.
Home-page: UNKNOWN
Author: Martijn Faassen
Author-email: faassen@startifact.com
License: ZPL 2.1
Platform: UNKNOWN
